axioms_fastapi/__init__.py
axioms_fastapi/_version.py
axioms_fastapi/config.py
axioms_fastapi/dependencies.py
axioms_fastapi/error.py
axioms_fastapi/helper.py
axioms_fastapi/middleware.py
axioms_fastapi-0.0.13.dist-info/licenses/LICENSE
axioms_fastapi-0.0.13.dist-info/METADATA
axioms_fastapi-0.0.13.dist-info/WHEEL
axioms_fastapi-0.0.13.dist-info/top_level.txt
axioms_fastapi-0.0.13.dist-info/RECORD
