Metadata-Version: 2.4
Name: axioms-fastapi
Version: 0.0.13
Summary: OAuth2/OIDC authentication and authorization for FastAPI APIs
Author-email: Abhishek Tiwari <abhishek@abstractclass.io>
License: MIT
Project-URL: Homepage, https://github.com/abhishektiwari/axioms-fastapi
Project-URL: Documentation, https://axioms-fastapi.abhishek-tiwari.com
Project-URL: Repository, https://github.com/abhishektiwari/axioms-fastapi
Project-URL: Issues, https://github.com/abhishektiwari/axioms-fastapi/issues
Keywords: fastapi,oauth2,oidc,jwt,authentication,authorization,axioms,security
Classifier: Development Status :: 4 - Beta
Classifier: Intended Audience :: Developers
Classifier: License :: OSI Approved :: MIT License
Classifier: Operating System :: OS Independent
Classifier: Programming Language :: Python :: 3
Classifier: Programming Language :: Python :: 3.8
Classifier: Programming Language :: Python :: 3.9
Classifier: Programming Language :: Python :: 3.10
Classifier: Programming Language :: Python :: 3.11
Classifier: Programming Language :: Python :: 3.12
Classifier: Programming Language :: Python :: 3.13
Classifier: Topic :: Software Development :: Libraries :: Python Modules
Classifier: Topic :: Security
Classifier: Framework :: FastAPI
Requires-Python: >=3.8
License-File: LICENSE
Requires-Dist: fastapi>=0.100.0
Requires-Dist: pyjwt>=2.8.0
Requires-Dist: jwcrypto>=1.5.0
Requires-Dist: python-box>=7.0.0
Requires-Dist: pydantic-settings>=2.0.0
Provides-Extra: dev
Requires-Dist: black>=23.0.0; extra == "dev"
Requires-Dist: pytest>=7.4.0; extra == "dev"
Requires-Dist: pytest-cov>=4.1.0; extra == "dev"
Requires-Dist: pytest-asyncio>=0.21.0; extra == "dev"
Requires-Dist: httpx>=0.24.0; extra == "dev"
Requires-Dist: ruff>=0.1.0; extra == "dev"
Requires-Dist: build>=1.0.0; extra == "dev"
Requires-Dist: twine>=4.0.0; extra == "dev"
Requires-Dist: sphinx>=7.0.0; extra == "dev"
Requires-Dist: sphinx-book-theme>=1.0.0; extra == "dev"
Requires-Dist: sphinx-autobuild>=2021.3.14; extra == "dev"
Requires-Dist: sphinx-copybutton>=0.5.0; extra == "dev"
Requires-Dist: jwcrypto>=1.5.0; extra == "dev"
Requires-Dist: sqlmodel>=0.0.14; extra == "dev"
Dynamic: license-file
